cloudshell/__init__.py
cloudshell/cumulus/__init__.py
cloudshell/cumulus/linux/__init__.py
cloudshell/cumulus/linux/const.py
cloudshell/cumulus/linux/cli/__init__.py
cloudshell/cumulus/linux/cli/command_modes.py
cloudshell/cumulus/linux/cli/handler.py
cloudshell/cumulus/linux/command_actions/__init__.py
cloudshell/cumulus/linux/command_actions/firmware.py
cloudshell/cumulus/linux/command_actions/snmp.py
cloudshell/cumulus/linux/command_actions/system.py
cloudshell/cumulus/linux/command_templates/__init__.py
cloudshell/cumulus/linux/command_templates/enable_disable_snmp.py
cloudshell/cumulus/linux/command_templates/firmware.py
cloudshell/cumulus/linux/command_templates/system.py
cloudshell/cumulus/linux/connectivity/__init__.py
cloudshell/cumulus/linux/connectivity/iface_config_handler.py
cloudshell/cumulus/linux/connectivity/vlan_config_handler.py
cloudshell/cumulus/linux/flows/__init__.py
cloudshell/cumulus/linux/flows/autoload_flow.py
cloudshell/cumulus/linux/flows/configuration_flow.py
cloudshell/cumulus/linux/flows/connectivity_flow.py
cloudshell/cumulus/linux/flows/enable_disable_snmp_flow.py
cloudshell/cumulus/linux/flows/load_firmware.py
cloudshell/cumulus/linux/flows/shutdown.py
cloudshell/cumulus/linux/snmp/__init__.py
cloudshell/cumulus/linux/snmp/snmp_autoload.py
cloudshell/cumulus/linux/snmp/snmp_conf_handler.py
cloudshell/cumulus/linux/snmp/snmp_if_table.py
cloudshell/cumulus/linux/snmp/system_info.py
cloudshell/cumulus/linux/utils/__init__.py
cloudshell/cumulus/linux/utils/cached_property.py
tests/__init__.py
tests/cumulus/__init__.py
tests/cumulus/linux/__init__.py
tests/cumulus/linux/conftest.py
tests/cumulus/linux/connectivity/__init__.py
tests/cumulus/linux/connectivity/test_vlan_config_handler.py
tests/cumulus/linux/flows/__init__.py
tests/cumulus/linux/flows/test_connectivity.py
tests/cumulus/linux/snmp/__init__.py
tests/cumulus/linux/snmp/test_snmp_conf.py
cloudshell_cumulus_linux-2.0.0.dist-info/METADATA
cloudshell_cumulus_linux-2.0.0.dist-info/WHEEL
cloudshell_cumulus_linux-2.0.0.dist-info/top_level.txt
cloudshell_cumulus_linux-2.0.0.dist-info/RECORD
